setup.py
spotify2piratebay/__init__.py
spotify2piratebay/runner.py
spotify2piratebay/utils.py
spotify2piratebay.egg-info/PKG-INFO
spotify2piratebay.egg-info/SOURCES.txt
spotify2piratebay.egg-info/dependency_links.txt
spotify2piratebay.egg-info/entry_points.txt
spotify2piratebay.egg-info/requires.txt
spotify2piratebay.egg-info/top_level.txt