Metadata-Version: 1.1
Name: spotify2piratebay
Version: 0.1
Summary: Download your Spotify music using the Pirate Bay
Home-page: http://github.com/dokterbob/spotify2piratebay/
Author: Mathijs de Bruin
Author-email: mathijs@visualspace.nl
License: UNKNOWN
Platform: UNKNOWN
Classifier: Development Status :: 3 - Alpha
Classifier: Environment :: Console
Classifier: Intended Audience :: Developers
Classifier: License :: Public Domain
Classifier: Operating System :: OS Independent
Classifier: Programming Language :: Python
Classifier: Topic :: Utilities
